plrt/__init__.py
plrt/plrt.py
py_plrt-0.0.3.dist-info/LICENSE
py_plrt-0.0.3.dist-info/METADATA
py_plrt-0.0.3.dist-info/WHEEL
py_plrt-0.0.3.dist-info/top_level.txt
py_plrt-0.0.3.dist-info/RECORD
