Metadata-Version: 2.1
Name: py-plrt
Version: 0.0.3
Summary: Machine learning model that uses linear regression equations in the leaf nodes of a decision tree.
Home-page: https://github.com/lcford2/py-plrt
Author: Lucas Ford
Author-email: lcford185@gmail.com
Project-URL: Bug Tracker, https://github.com/lcford2/py-plrt/issues
Classifier: Programming Language :: Python :: 3
Classifier: License :: OSI Approved :: MIT License
Classifier: Operating System :: OS Independent
Requires-Python: >=3.6
License-File: LICENSE
Requires-Dist: numpy
Requires-Dist: pandas
Requires-Dist: scikit-learn
Requires-Dist: scipy
